mibiremo/__init__.py
mibiremo/irmresult.py
mibiremo/phreeqc.py
mibiremo/semilagsolver.py
mibiremo/database/README.md
mibiremo/database/mibirem.dat
mibiremo/database/minteq.v4.dat
mibiremo/database/phreeqc.dat
mibiremo/database/wateq4f.dat
mibiremo/lib/PhreeqcRM.dll
mibiremo/lib/PhreeqcRM.so
mibiremo/lib/README.md
mibiremo-0.1.0.dist-info/licenses/LICENSE
mibiremo-0.1.0.dist-info/METADATA
mibiremo-0.1.0.dist-info/WHEEL
mibiremo-0.1.0.dist-info/top_level.txt
mibiremo-0.1.0.dist-info/RECORD
