Metadata-Version: 2.4
Name: mibiremo
Version: 0.1.0
Summary: Microbiome Bioremediation Reaction Module: a Python interface to PhreeqcRM library
Author-email: Matteo Masi <matteo@dndbiotech.it>
License:                                  Apache License
Project-URL: Repository, https://github.com/MiBiPret/mibiremo
Project-URL: Issues, https://github.com/MiBiPret/mibiremo/issues
Project-URL: ReadTheDocs, https://mibiremo.readthedocs.io
Keywords: Microbiome, Bioremediation, Chemical Reaction, Geochemical Engineering
Classifier: Development Status :: 2 - Pre-Alpha
Classifier: Intended Audience :: Developers
Classifier: Intended Audience :: Science/Research
Classifier: License :: OSI Approved :: Apache Software License
Classifier: Natural Language :: English
Classifier: Programming Language :: Python :: 3
Classifier: Programming Language :: Python :: 3.10
Classifier: Programming Language :: Python :: 3.11
Classifier: Programming Language :: Python :: 3.12
Requires-Python: >=3.10
License-File: LICENSE
Requires-Dist: pandas
Requires-Dist: numpy
Requires-Dist: matplotlib
Requires-Dist: pyqt5
Requires-Dist: scipy
Provides-Extra: dev
Requires-Dist: build; extra == "dev"
Requires-Dist: bump-my-version; extra == "dev"
Requires-Dist: coverage[toml]; extra == "dev"
Requires-Dist: pytest; extra == "dev"
Requires-Dist: pytest-cov; extra == "dev"
Requires-Dist: ruff; extra == "dev"
Requires-Dist: tox; extra == "dev"
Provides-Extra: doc
Requires-Dist: mkdocs>=1.4.2; extra == "doc"
Requires-Dist: mkdocs-material>=8.2.7; extra == "doc"
Requires-Dist: mkdocstrings[python]==0.27.0; extra == "doc"
Requires-Dist: mdx-include>=1.4.1; extra == "doc"
Requires-Dist: mkdocs-markdownextradata-plugin>=0.2.5; extra == "doc"
Provides-Extra: publishing
Requires-Dist: build; extra == "publishing"
Requires-Dist: twine; extra == "publishing"
Requires-Dist: wheel; extra == "publishing"
Dynamic: license-file
